markprompt/__init__.py
markprompt/client.py
markprompt/core/__init__.py
markprompt/core/logger.py
markprompt/core/models.py
markprompt/core/parser.py
markprompt/core/tools.py
markprompt-0.4.9.dist-info/METADATA
markprompt-0.4.9.dist-info/WHEEL
markprompt-0.4.9.dist-info/RECORD
